sogon/__init__.py
sogon/audio_manager.py
sogon/cli.py
sogon/corrector.py
sogon/downloader.py
sogon/main_processor.py
sogon/transcriber.py
sogon/api/__init__.py
sogon/api/config.py
sogon/api/main.py
sogon/config/__init__.py
sogon/config/settings.py
sogon/config/validation.py
sogon/exceptions/__init__.py
sogon/exceptions/audio.py
sogon/exceptions/base.py
sogon/exceptions/correction.py
sogon/exceptions/job.py
sogon/exceptions/transcription.py
sogon/models/__init__.py
sogon/models/audio.py
sogon/models/correction.py
sogon/models/job.py
sogon/models/transcription.py
sogon/models/translation.py
sogon/repositories/__init__.py
sogon/repositories/cache_repository.py
sogon/repositories/file_repository.py
sogon/repositories/interfaces.py
sogon/repositories/job_repository.py
sogon/services/__init__.py
sogon/services/audio_service.py
sogon/services/correction_service.py
sogon/services/file_service.py
sogon/services/interfaces.py
sogon/services/transcription_service.py
sogon/services/translation_service.py
sogon/services/workflow_service.py
sogon/services/youtube_service.py
sogon/utils/__init__.py
sogon/utils/file_ops.py
sogon/utils/logging.py
sogon-0.1.2.dist-info/METADATA
sogon-0.1.2.dist-info/WHEEL
sogon-0.1.2.dist-info/entry_points.txt
sogon-0.1.2.dist-info/licenses/LICENSE
sogon-0.1.2.dist-info/RECORD
