Metadata-Version: 2.4
Name: sogon
Version: 0.1.2
Summary: AI-powered subtitle generator from YouTube URLs or local media files
Project-URL: Repository, https://github.com/e7217/sogon
Author-email: Changyong Um <eum6211@gmail.com>
License-Expression: MIT
License-File: LICENSE
Classifier: License :: OSI Approved :: MIT License
Classifier: Programming Language :: Python :: 3
Requires-Python: >=3.9
Requires-Dist: fastapi>=0.104.0
Requires-Dist: groq>=0.26.0
Requires-Dist: openai>=1.58.1
Requires-Dist: pydantic-settings>=2.9.1
Requires-Dist: pydub>=0.25.1
Requires-Dist: python-dotenv>=1.0.0
Requires-Dist: python-multipart>=0.0.6
Requires-Dist: tqdm>=4.67.1
Requires-Dist: typer>=0.12.0
Requires-Dist: uvicorn>=0.24.0
Requires-Dist: yt-dlp>=2024.3.10
Provides-Extra: dev
Requires-Dist: pytest-mock>=3.10.0; extra == 'dev'
Requires-Dist: pytest>=7.0.0; extra == 'dev'
